keybert/__init__.py
keybert/_highlight.py
keybert/_llm.py
keybert/_maxsum.py
keybert/_mmr.py
keybert/_model.py
keybert/_utils.py
keybert/backend/__init__.py
keybert/backend/_base.py
keybert/backend/_flair.py
keybert/backend/_gensim.py
keybert/backend/_hftransformers.py
keybert/backend/_sentencetransformers.py
keybert/backend/_spacy.py
keybert/backend/_use.py
keybert/backend/_utils.py
keybert/llm/__init__.py
keybert/llm/_base.py
keybert/llm/_cohere.py
keybert/llm/_langchain.py
keybert/llm/_litellm.py
keybert/llm/_openai.py
keybert/llm/_textgeneration.py
keybert/llm/_utils.py
keybert-0.8.5.dist-info/LICENSE
keybert-0.8.5.dist-info/METADATA
keybert-0.8.5.dist-info/WHEEL
keybert-0.8.5.dist-info/top_level.txt
keybert-0.8.5.dist-info/RECORD
