Metadata-Version: 2.1
Name: keybert
Version: 0.8.5
Summary: KeyBERT performs keyword extraction with state-of-the-art transformer models.
Author-email: Maarten Grootendorst <maartengrootendorst@gmail.com>
License: MIT License
Project-URL: Documentation, https://maartengr.github.io/KeyBERT/
Project-URL: Homepage, https://github.com/MaartenGr/KeyBERT
Project-URL: Issues, https://github.com/MaartenGr/KeyBERT/issues
Project-URL: Repository, https://github.com/MaartenGr/KeyBERT.git
Keywords: nlp,bert,keyword,extraction,embeddings
Classifier: Intended Audience :: Developers
Classifier: Intended Audience :: Science/Research
Classifier: License :: OSI Approved :: MIT License
Classifier: Operating System :: MacOS
Classifier: Operating System :: Microsoft :: Windows
Classifier: Operating System :: POSIX
Classifier: Operating System :: Unix
Classifier: Programming Language :: Python
Classifier: Programming Language :: Python :: 3.8
Classifier: Programming Language :: Python :: 3.9
Classifier: Programming Language :: Python :: 3.10
Classifier: Programming Language :: Python :: 3.11
Classifier: Programming Language :: Python :: 3.12
Classifier: Topic :: Scientific/Engineering
Classifier: Topic :: Scientific/Engineering :: Artificial Intelligence
Requires-Python: >=3.8
License-File: LICENSE
Requires-Dist: numpy>=1.18.5
Requires-Dist: rich>=10.4.0
Requires-Dist: scikit-learn>=0.22.2
Requires-Dist: sentence-transformers>=0.3.8
Provides-Extra: dev
Requires-Dist: keybert[docs,test]; extra == "dev"
Provides-Extra: docs
Requires-Dist: mkdocs-material>=4.6.3; extra == "docs"
Requires-Dist: mkdocs>=1.1; extra == "docs"
Requires-Dist: mkdocstrings>=0.8.0; extra == "docs"
Provides-Extra: flair
Requires-Dist: flair>=0.7; extra == "flair"
Requires-Dist: torch>=1.4.0; extra == "flair"
Requires-Dist: transformers>=3.5.1; extra == "flair"
Provides-Extra: gensim
Requires-Dist: gensim>=3.6.0; extra == "gensim"
Provides-Extra: spacy
Requires-Dist: spacy>=3.0.1; extra == "spacy"
Provides-Extra: test
Requires-Dist: black>=19.3b0; extra == "test"
Requires-Dist: flake8>=3.6.0; extra == "test"
Requires-Dist: pre-commit>=2.2.0; extra == "test"
Requires-Dist: pytest-cov>=2.6.1; extra == "test"
Requires-Dist: pytest>=5.4.3; extra == "test"
Provides-Extra: use
Requires-Dist: tensorflow; extra == "use"
Requires-Dist: tensorflow_hub; extra == "use"
Requires-Dist: tensorflow_text; extra == "use"
